noqui/__init__.py
noqui/sleep_sort.py
noqui-0.0.2.dist-info/WHEEL
noqui-0.0.2.dist-info/METADATA
noqui-0.0.2.dist-info/RECORD
