Metadata-Version: 2.1
Name: noqui
Version: 0.0.2
Summary: Implementation of unusual things
License: MIT
Author: Roberto Alsina
Author-email: roberto.alsina@gmail.com
Requires-Python: >=3.10,<4.0
Classifier: License :: OSI Approved :: MIT License
Classifier: Programming Language :: Python :: 3
Classifier: Programming Language :: Python :: 3.10
